nanograd/__init__.py
nanograd/autograd_engine.py
nanograd/device.py
nanograd/tensor.py
nanograd/nn/__init__.py
nanograd/nn/conv_ops.py
nanograd/nn/functional.py
nanograd/nn/module.py
nanograd/nn/ops_cpu.py
nanograd/nn/ops_gpu.py
nanograd/optim/__init__.py
nanograd/optim/optimizer.py
nanograd/viz/__init__.py
nanograd/viz/comp_graph.py
nanograd-1.0.4.dist-info/LICENSE
nanograd-1.0.4.dist-info/METADATA
nanograd-1.0.4.dist-info/WHEEL
nanograd-1.0.4.dist-info/top_level.txt
nanograd-1.0.4.dist-info/RECORD
