Metadata-Version: 2.1
Name: nanograd
Version: 1.0.4
Summary: A lightweight deep learning framework
Home-page: https://github.com/PABannier/nanograd
Author: PAB
Author-email: pierre-antoine.bannier@polytechnique.edu
License: MIT
Platform: UNKNOWN
Classifier: License :: OSI Approved :: MIT License
Classifier: Programming Language :: Python :: 3
Classifier: Programming Language :: Python :: 3.9
Requires-Dist: numpy
Requires-Dist: matplotlib
Requires-Dist: graphviz
Requires-Dist: pyopencl
Requires-Dist: mako
